l1m/__init__.py
l1m/client.py
l1m_dot_io-0.1.6.dist-info/LICENSE
l1m_dot_io-0.1.6.dist-info/METADATA
l1m_dot_io-0.1.6.dist-info/WHEEL
l1m_dot_io-0.1.6.dist-info/top_level.txt
l1m_dot_io-0.1.6.dist-info/RECORD
