Metadata-Version: 2.2
Name: l1m-dot-io
Version: 0.1.6
Summary: Python SDK for L1M
Project-URL: Homepage, https://github.com/inferablehq/l1m
Project-URL: Bug Tracker, https://github.com/inferablehq/l1m/issues
Classifier: Programming Language :: Python :: 3
Classifier: License :: OSI Approved :: MIT License
Classifier: Operating System :: OS Independent
Requires-Python: >=3.8
License-File: LICENSE
Requires-Dist: requests>=2.28.0
Requires-Dist: pydantic>=2.0.0
Requires-Dist: python-dotenv>=1.0.0
